<?xml version="1.0" encoding="UTF-8"?><adapter xmlns:xi="http://www.w3.org/2001/XInclude">
  <unique-id>FS-FS-modified-test9</unique-id>
  <start-up-event-imp>com.adaptris.core.event.StandardAdapterStartUpEvent</start-up-event-imp>
  <heartbeat-event-imp>com.adaptris.core.HeartbeatEvent</heartbeat-event-imp>
  <log-handler class="null-log-handler">
    <unique-id>tender-shannon</unique-id>
  </log-handler>
  <shared-components>
    <connections/>
    <services/>
  </shared-components>
  <event-handler class="default-event-handler">
    <unique-id>DefaultEventHandler</unique-id>
    <connection class="null-connection">
      <unique-id>NullConnection-9723862</unique-id>
    </connection>
    <producer class="null-message-producer">
      <unique-id>NullMessageProducer-5178137</unique-id>
    </producer>
  </event-handler>
  <message-error-handler class="null-processing-exception-handler">
    <unique-id>NullProcessingExceptionHandler-9650991</unique-id>
  </message-error-handler>
  <failed-message-retrier class="no-retries">
    <unique-id>sharp-archimedes</unique-id>
  </failed-message-retrier>
  <channel-list>
    <channel>
      <consume-connection class="null-connection">
        <unique-id>NullConnection-118358</unique-id>
      </consume-connection>
      <produce-connection class="null-connection">
        <unique-id>NullConnection-2385428</unique-id>
      </produce-connection>
      <workflow-list>
        <xi:include href="borat-includes/workflow.xml"/>
      </workflow-list>
      <unique-id>Channel7</unique-id>
    </channel>
  </channel-list>
  <message-error-digester class="standard-message-error-digester">
    <unique-id>ErrorDigest</unique-id>
    <digest-max-size>100</digest-max-size>
  </message-error-digester>
</adapter>