{
  "name" : "2019-03-06T08.27.25",
  "variableSets" : {
    "default" : { },
    "staging" : { },
    "live" : { },
    "test" : { }
  },
  "variableXpaths" : {
    "/adapter/channel-list/channel[unique-id=\"Channel6\"]/workflow-list/standard-workflow[unique-id=\"Workflow3\"]/producer/destination/destination" : "${produceDest}",
    "/adapter/channel-list/channel[unique-id=\"Channel6\"]/workflow-list/standard-workflow[unique-id=\"Workflow3\"]/consumer/destination/destination" : "${consumeDest}",
    "/adapter/channel-list/channel[unique-id=\"Channel6\"]/workflow-list/standard-workflow[unique-id=\"Workflow3\"]/service-collection/services/add-metadata-service[unique-id=\"backstabbing-morse\"]/metadata-element[1]/value" : "${metadataValue}"
  },
  "uidInXincludeCompntListFileName" : true,
  "xincludeXpaths" : {
    "/adapter/channel-list/channel/consume-connection" : "consume-connection",
    "/adapter/channel-list/channel/produce-connection" : "produce-connection",
    "/adapter/channel-list/channel/workflow-list/*[contains(name(),'-workflow')]" : "workflow",
    "/adapter/event-handler" : "event-handler"
  },
  "additionalFiles" : {
    "bootstrap.properties" : "bootstrap.properties"
  },
  "optionalComponentsInUse" : [ ],
  "structured" : true
}